jalalicrontab/__init__.py
jalalicrontab/schedule.py
jalalicrontab/time.py
celery_jalalicrontab-1.0.3.dist-info/METADATA
celery_jalalicrontab-1.0.3.dist-info/WHEEL
celery_jalalicrontab-1.0.3.dist-info/top_level.txt
celery_jalalicrontab-1.0.3.dist-info/RECORD
