Metadata-Version: 2.1
Name: celery-jalalicrontab
Version: 1.0.3
Summary: A Celery schedule corntab which is work with jalali calendar
Home-page: https://github.com/saber-solooki/jalalicrontab
Author: Saber Solooki
Author-email: saber.solooki@gmail.com
License: Apache License, Version 2.0
Keywords: python,celery,schedule,jalali,calendar
Platform: UNKNOWN
Classifier: Development Status :: 5 - Production/Stable
Classifier: License :: OSI Approved :: Apache Software License
Classifier: Topic :: System :: Distributed Computing
Classifier: Topic :: Software Development :: Object Brokering
Classifier: Programming Language :: Python
Classifier: Programming Language :: Python :: 3
Classifier: Programming Language :: Python :: 3.6
Classifier: Programming Language :: Python :: 3.7
Classifier: Programming Language :: Python :: 3.8
Classifier: Programming Language :: Python :: 3.9
Classifier: Programming Language :: Python :: Implementation :: CPython
Classifier: Operating System :: OS Independent
Requires-Dist: celery (>=4.2)
Requires-Dist: jdatetime (~=3.6.0)
